{
  "experiment_name": "vqc_fourier_series_expressivity",
  "outdir": "results",
  "seed": 1337,
  "device": "cpu",
  "data": {
    "x_start": -9.42477796076938,
    "x_end": 9.42477796076938,
    "step": 0.05,
    "coefficients": [
      {"n": 0, "real": 0.2, "imag": 0.0},
      {"n": 1, "real": 0.69, "imag": 0.52},
      {"n": 2, "real": 0.81, "imag": 0.41},
      {"n": 3, "real": 0.68, "imag": 0.82}
    ]
  },
  "model": {
    "num_modes": 3,
    "input_size": 1,
    "scale_type": "/pi",
    "trainable_parameters": ["theta"],
    "input_parameters": ["px"],
    "no_bunching": false,
    "output_mapping_strategy": "LINEAR"
  },
  "training": {
    "epochs": 100,
    "batch_size": 32,
    "learning_rate": 0.02,
    "betas": [0.9, 0.999],
    "num_runs": 2,
    "initial_states": [[1, 0, 0], [1, 1, 1]],
    "progress_bar": true
  },
  "plotting": {
    "colors": ["#1f77b4", "#ff7f0e", "#d62728"]
  },
  "logging": {
    "save_training_curves": true,
    "save_learned_functions": true
  }
}
